onionrequests/OnionQueue.py
onionrequests/OnionSession.py
onionrequests/TorPort.py
onionrequests/__init__.py
onionrequests/tests.py
onionrequests/exceptions/CouldNotFindTorPortException.py
onionrequests/exceptions/InvalidHTTPMethodException.py
onionrequests/exceptions/__init__.py
onionrequests-0.2.6.dist-info/licenses/LICENSE
onionrequests-0.2.6.dist-info/METADATA
onionrequests-0.2.6.dist-info/WHEEL
onionrequests-0.2.6.dist-info/top_level.txt
onionrequests-0.2.6.dist-info/RECORD
