Metadata-Version: 2.4
Name: onionrequests
Version: 0.2.6
Summary: Anonymous HTTP requests via TOR
Author: Ethan Samford
Classifier: Programming Language :: Python :: 3
Classifier: License :: OSI Approved :: MIT License
Classifier: Operating System :: OS Independent
Requires-Python: >=3
License-File: LICENSE
Requires-Dist: requests[socks]
Dynamic: license-file
